zlogo/__init__.py
zlogo/config/__init__.py
zlogo/config/defaults.py
zlogo/config/zlogo.logorc
zlogo/engine/__init__.py
zlogo/engine/cli.py
zlogo/tool/__init__.py
zlogo/tool/logo
zlogo/util/__init__.py
zlogo/util/misc.py
zlogo/util/utility.py
zlogo-1.0.2.dist-info/LICENSE
zlogo-1.0.2.dist-info/METADATA
zlogo-1.0.2.dist-info/WHEEL
zlogo-1.0.2.dist-info/entry_points.txt
zlogo-1.0.2.dist-info/top_level.txt
zlogo-1.0.2.dist-info/RECORD
