Metadata-Version: 2.2
Name: zlogo
Version: 1.0.2
Summary: A simple logo generator that creates SVG and PNG logos from text.
Home-page: https://github.com/zjykzj/zlogo
Author: zj
Author-email: wy163zhuj@163.com
Classifier: Programming Language :: Python :: 3
Classifier: Operating System :: OS Independent
Classifier: License :: OSI Approved :: Apache Software License
Classifier: Topic :: Multimedia :: Graphics
Classifier: Intended Audience :: Developers
Requires-Python: >=3.6
License-File: LICENSE
Requires-Dist: cairosvg>=2.5.0
Provides-Extra: dev
Requires-Dist: twine; extra == "dev"
Requires-Dist: wheel; extra == "dev"
Requires-Dist: setuptools; extra == "dev"
Dynamic: author
Dynamic: author-email
Dynamic: classifier
Dynamic: description
Dynamic: description-content-type
Dynamic: home-page
Dynamic: provides-extra
Dynamic: requires-dist
Dynamic: requires-python
Dynamic: summary
